setup.cfg
setup.py
languagesda/__init__.py
languagesda.egg-info/PKG-INFO
languagesda.egg-info/SOURCES.txt
languagesda.egg-info/dependency_links.txt
languagesda.egg-info/requires.txt
languagesda.egg-info/top_level.txt