Metadata-Version: 2.2
Name: languagesda
Version: 2.5
Author: development
Author-email: agcs-development@rambler.ru
Requires-Python: >=3.11
Requires-Dist: tkinter
Dynamic: author
Dynamic: author-email
Dynamic: requires-dist
Dynamic: requires-python
